frogweather/__init__.py
frogweather/frogweather.py
frogweather-0.5.dist-info/METADATA
frogweather-0.5.dist-info/WHEEL
frogweather-0.5.dist-info/top_level.txt
frogweather-0.5.dist-info/RECORD
