Metadata-Version: 2.1
Name: frogweather
Version: 0.5
Summary: Frog-themed weather station
Home-page: https://github.com/acschaefer/frogweather
Author: Alexander Schaefer
Author-email: acschaefer@users.noreply.github.com
Maintainer: Alexander Schaefer
License: MIT
Platform: UNKNOWN
Classifier: License :: OSI Approved :: MIT License
Classifier: Programming Language :: Python :: 2
Classifier: Programming Language :: Python :: 2.6
Classifier: Programming Language :: Python :: 2.7
Classifier: Operating System :: OS Independent
Requires-Dist: darkskylib
Requires-Dist: PyYAML
Requires-Dist: pygame
Requires-Dist: duallog
